py_SAINT/README.md
py_SAINT/__init__.py
py_SAINT/pypi_readme.md
py_SAINT/pypi_readme.txt
py_SAINT/STAGE1/__init__.py
py_SAINT/STAGE1/concatate_mk.py
py_SAINT/STAGE1/copyfiles2dire.py
py_SAINT/STAGE1/dataloader.py
py_SAINT/STAGE1/interpolation.py
py_SAINT/STAGE1/local_temp_exe.py
py_SAINT/STAGE1/main.py
py_SAINT/STAGE1/match_files2dir.py
py_SAINT/STAGE1/memory_test.py
py_SAINT/STAGE1/model_best.pt
py_SAINT/STAGE1/nii2pickle.py
py_SAINT/STAGE1/option.py
py_SAINT/STAGE1/ori2crude.py
py_SAINT/STAGE1/pt2nii.py
py_SAINT/STAGE1/show_img_mk.py
py_SAINT/STAGE1/template.py
py_SAINT/STAGE1/trainer.py
py_SAINT/STAGE1/utility.py
py_SAINT/STAGE1/data/__init__.py
py_SAINT/STAGE1/data/backup_srdata.py
py_SAINT/STAGE1/data/common.py
py_SAINT/STAGE1/data/srdata.py
py_SAINT/STAGE1/data/test.py
py_SAINT/STAGE1/data/train.py
py_SAINT/STAGE1/loss/__init__.py
py_SAINT/STAGE1/loss/adversarial.py
py_SAINT/STAGE1/loss/discriminator.py
py_SAINT/STAGE1/loss/nlayerdiscriminator.py
py_SAINT/STAGE1/loss/vgg.py
py_SAINT/STAGE1/model/__init__.py
py_SAINT/STAGE1/model/baseline2d_rdn.py
py_SAINT/STAGE1/model/baseline3d_rdn.py
py_SAINT/STAGE1/model/common.py
py_SAINT/STAGE1/model/fuse_rdn.py
py_SAINT/STAGE1/model/ganimation.py
py_SAINT/STAGE1/model/lonwin.py
py_SAINT/STAGE1/model/mDCSRN.py
py_SAINT/STAGE1/model/mar_rdn.py
py_SAINT/STAGE1/model/meta_both.py
py_SAINT/STAGE1/model/meta_interp.py
py_SAINT/STAGE1/model/meta_multi.py
py_SAINT/STAGE1/model/meta_multi_extra.py
py_SAINT/STAGE1/model/meta_multi_x4.py
py_SAINT/STAGE1/model/meta_superv.py
py_SAINT/STAGE1/model/metardn.py
py_SAINT/STAGE1/model/msr_rdn.py
py_SAINT/STAGE1/model/rdn.py
py_SAINT/STAGE1/model/refine_rdn.py
py_SAINT/STAGE1/model/unet.py
py_SAINT/STAGE1/process/2d_to_3d_kernel.py
py_SAINT/STAGE1/process/2dcnn_dataset_test.py
py_SAINT/STAGE1/process/2dcnn_dataset_train.py
py_SAINT/STAGE1/process/3d_augment.py
py_SAINT/STAGE1/process/3d_psnr.py
py_SAINT/STAGE1/process/__init__.py
py_SAINT/STAGE1/process/add_interp_fuse.py
py_SAINT-1.7.0.dist-info/METADATA
py_SAINT-1.7.0.dist-info/WHEEL
py_SAINT-1.7.0.dist-info/top_level.txt
py_SAINT-1.7.0.dist-info/RECORD
