Metadata-Version: 2.1
Name: py-SAINT
Version: 1.7.0
Summary: SAINT
Home-page: UNKNOWN
Author: SMK
Author-email: 454297329@qq.com
License: UNKNOWN
Platform: UNKNOWN
Classifier: Programming Language :: Python :: 3
Classifier: License :: OSI Approved :: MIT License
Classifier: Operating System :: OS Independent
Requires-Python: >=3.6
